mychemtools/__init__.py
mychemtools/anti_checker.py
mychemtools/intro.py
mychemtools/prepare_data.py
mychemtools/reference.py
mychemtools-0.1.2.dist-info/METADATA
mychemtools-0.1.2.dist-info/WHEEL
mychemtools-0.1.2.dist-info/RECORD
