Metadata-Version: 2.1
Name: mychemtools
Version: 0.1.2
Summary: A package for building t5-antifungal website
License: MIT
Author: Yao-Chung Chen
Requires-Python: >=3.9,<4.0
Classifier: License :: OSI Approved :: MIT License
Classifier: Programming Language :: Python :: 3
Classifier: Programming Language :: Python :: 3.9
Classifier: Programming Language :: Python :: 3.10
Classifier: Programming Language :: Python :: 3.11
